SinglePort_RAM.v
module single_port_ram(
  input [7:0] data, // input data
  input [5:0] addr, // address
  input we,         // write enable
  input clk,        // clock
  output [7:0] q    // output data
);
  
  reg [7:0] ram [63:0];  // 8x64 bit RAM
  reg [5:0] addr_reg;    // address register
 
  always @(posedge clk) begin
    if (we)
      ram[addr] <= data; // Write data to RAM
    else
      addr_reg <= addr;  // Capture address
  end
 
  assign q = ram[addr_reg]; // Output data from RAM
  
endmodule

SinglePort_RAMTB.v
module single_port_ram_tb;
  reg [7:0] data;  // input data
  reg [5:0] addr;  // address
  reg we;          // write enable
  reg clk;         // clock
  wire [7:0] q;    // output data 	
  
  // Instantiate the single_port_ram module
  single_port_ram spr1(
    .data(data),
    .addr(addr),
    .we(we),
    .clk(clk),
    .q(q)
  );
  
  initial begin
    $dumpfile("single_port_ram_dump.vcd");
    $dumpvars(1, single_port_ram_tb);       
    clk = 1'b1;
    forever #5 clk = ~clk; // Clock generation
  end
  
  initial begin
    // Test sequence
    data = 8'h01; addr = 5'd0; we = 1'b1; #10;
    data = 8'h02; addr = 5'd1; #10;
    data = 8'h03; addr = 5'd2; #10;
    addr = 5'd0; we = 1'b0; #10;
    addr = 5'd1; #10;
    addr = 5'd2; #10;
    data = 8'h04; addr = 5'd1; we = 1'b1; #10;
    addr = 5'd1; we = 1'b0; #10;
    addr = 5'd3; #10;
  end
  
  initial #90 $stop;
  
endmodule

SinglePort_RAM_dump.vcd
$date
	Wed Dec 18 00:14:58 2024
$end
$version
	Icarus Verilog
$end
$timescale
	1s
$end
$scope module single_port_ram_tb $end
$var wire 8 ! q [7:0] $end
$var reg 6 " addr [5:0] $end
$var reg 1 # clk $end
$var reg 8 $ data [7:0] $end
$var reg 1 % we $end
$upscope $end
$enddefinitions $end
$comment Show the parameter values. $end
$dumpall
$end
#0
$dumpvars
1%
b1 $
1#
b0 "
bx !
$end
#5
0#
#10
1#
b1 "
b10 $
#15
0#
#20
1#
b10 "
b11 $
#25
0#
#30
b1 !
1#
0%
b0 "
#35
0#
#40
b10 !
1#
b1 "
#45
0#
#50
b11 !
1#
b10 "
#55
0#
#60
1#
1%
b1 "
b100 $
#65
0#
#70
b100 !
1#
0%
#75
0#
#80
bx !
1#
b11 "
